apistats/__init__.py
apistats/admin.py
apistats/loader.py
apistats/middlewares.py
apistats/models.py
apistats/tests.py
apistats/migrations/0001_initial.py
apistats/migrations/0002_auto_20201008_2203.py
apistats/migrations/0003_apistat_domain.py
apistats/migrations/0004_auto_20201009_1151.py
apistats/migrations/0005_auto_20201009_1242.py
apistats/migrations/__init__.py
apistats-0.4.1.dist-info/LICENSE
apistats-0.4.1.dist-info/METADATA
apistats-0.4.1.dist-info/WHEEL
apistats-0.4.1.dist-info/top_level.txt
apistats-0.4.1.dist-info/RECORD
