Metadata-Version: 2.1
Name: apistats
Version: 0.4.1
Summary: Simple django module with a middleware to track calls to django backend.
Home-page: UNKNOWN
Author: Frédéric MEUROU
Author-email: fm@peabytes.me
License: UNKNOWN
Platform: UNKNOWN
Classifier: Intended Audience :: Information Technology
Classifier: Environment :: Web Environment
Classifier: Development Status :: 4 - Beta
Classifier: Framework :: Django
Classifier: Framework :: Django :: 3.0
Classifier: Operating System :: OS Independent
Classifier: Programming Language :: Python
Classifier: Programming Language :: Python :: 3
Classifier: Programming Language :: Python :: 3 :: Only
Classifier: Topic :: Internet :: WWW/HTTP
Classifier: Topic :: System :: Logging
Classifier: Topic :: System :: Monitoring
Classifier: Topic :: System :: Logging
Classifier: License :: OSI Approved :: MIT License
Requires-Python: >3.7.0
Requires-Dist: Django (~=3.0)
